html_logging_tool-0.1.2.dist-info/licenses/LICENSE
htmllogger/__init__.py
htmllogger/config.py
htmllogger/core.py
htmllogger/html_template.py
htmllogger/utils.py
htmllogger/writer.py
html_logging_tool-0.1.2.dist-info/METADATA
html_logging_tool-0.1.2.dist-info/WHEEL
html_logging_tool-0.1.2.dist-info/top_level.txt
html_logging_tool-0.1.2.dist-info/RECORD
