Metadata-Version: 2.4
Name: html-logging-tool
Version: 0.1.2
Summary: Biblioteca para geração de logs em HTML com suporte a cores, rotação e filtros via JavaScript.
Home-page: https://github.com/rphpires/html-logging-tool
Author: Raphael Pires
Author-email: Raphael Pires Nome <rphspires@gmail.com>
License-Expression: MIT
Project-URL: Homepage, https://github.com/rphpires/html-logging-tool
Project-URL: Bug Tracker, https://github.com/rphpires/html-logging-tool/issues
Keywords: logging,html,logger,logs,colors,trace
Classifier: Programming Language :: Python :: 3
Classifier: Operating System :: OS Independent
Classifier: Topic :: System :: Logging
Requires-Python: >=3.8
License-File: LICENSE
Dynamic: license-file
